rtl/alu_opcodes.vh
// alu_opcodes.vh — ALU operation code definitions

`define ALU_ADD   5'd0
`define ALU_SUB   5'd1
`define ALU_AND   5'd2
`define ALU_OR    5'd3
`define ALU_XOR   5'd4
`define ALU_SLL   5'd5
`define ALU_SRL   5'd6
`define ALU_SRA   5'd7
`define ALU_SLT   5'd8
`define ALU_SLTU  5'd9

rtl/alu64.v
`include "alu_opcodes.vh"  // Define your opcodes here

module alu64 (
    input  logic [63:0] a,         // Operand A
    input  logic [63:0] b,         // Operand B
    input  logic [4:0]  opcode,    // ALU operation selector
    output logic [63:0] result,    // Result of operation
    output logic        zero,      // 1 if result == 0
    output logic        negative,  // 1 if result MSB is 1
    output logic        carry_out, // Carry bit from add/sub
    output logic        overflow   // Overflow indicator
);

    logic [63:0] sum, diff;
    logic        carry_add, carry_sub;

    always_comb begin
        // Initialize all signals to avoid latches
        sum       = 64'd0;
        diff      = 64'd0;
        carry_add = 1'b0;
        carry_sub = 1'b0;
        zero      = 1'b0;
        negative  = 1'b0;

        result    = 64'd0;
        carry_out = 1'b0;
        overflow  = 1'b0;

        case (opcode)
            `ALU_ADD: begin
                {carry_add, sum} = a + b;
                result    = sum;
                carry_out = carry_add;
                overflow  = (a[63] == b[63]) && (result[63] != a[63]);
            end

            `ALU_SUB: begin
                {carry_sub, diff} = a - b;
                result    = diff;
                carry_out = carry_sub;
                overflow  = (a[63] != b[63]) && (result[63] != a[63]);
            end

            `ALU_AND:  result = a & b;
            `ALU_OR:   result = a | b;
            `ALU_XOR:  result = a ^ b;
            `ALU_SLL:  result = a << b[5:0];
            `ALU_SRL:  result = a >> b[5:0];
            `ALU_SRA:  result = $signed(a) >>> b[5:0];
            `ALU_SLT:  result = ($signed(a) < $signed(b)) ? 64'd1 : 64'd0;
            `ALU_SLTU: result = (a < b) ? 64'd1 : 64'd0;

            default: result = 64'd0;
        endcase

        zero     = (result == 64'd0);
        negative = result[63];
    end

endmodule





/*
module(
    input logic [63:0] a,
    input logic [63:0] b,
    input logic [4:0] opcode,
    output logic [63:0] result,
    output logic zero,
    output logic carry_out,
    output logic overflow,
    output logic negative,   
);

logic input [63:0] sum;
logic input [63:0] diff;
logic input carry_add;
logic input carry_sub;


assign{carry_add, sum} = a + b;
assign{carry_sub, diff} = a - b;


always_comb begin
    result = 63'b0;
    overflow = 1'b0;
    carry_out = 1'b0;

case (opcode)
    `ALU_ADD: begin
      result = sum;
      carry_out = carry_add;
      overflow = (a[63] == b[63]) && (result[63] != a[63];);
    end

    `ALU_SUB: begin
        reult = diff;
        carry_out = carry_sub;
        overflow = (a[63] == b[63]) && (result[63] != a[63]);
    end

`include "alu_opcodes.vh"  // Define your opcodes here

module alu64 (
    input  logic [63:0] a,        // Operand A
    input  logic [63:0] b,        // Operand B
    input  logic [4:0]  opcode,   // Operation selector (you can widen if needed)
    output logic [63:0] result,   // ALU result
    output logic        zero,     // Result is zero
    output logic        negative, // MSB of result
    output logic        carry_out,// Carry from addition/subtraction
    output logic        overflow  // Signed overflow
*/

wave.vcd
$version Generated by VerilatedVcd $end
$timescale 1ps $end
 $scope module TOP $end
  $var wire 64 ) a [63:0] $end
  $var wire 64 + b [63:0] $end
  $var wire 5 - opcode [4:0] $end
  $var wire 64 . result [63:0] $end
  $var wire 1 0 zero $end
  $var wire 1 1 negative $end
  $var wire 1 2 carry_out $end
  $var wire 1 3 overflow $end
  $scope module alu64 $end
   $var wire 64 ) a [63:0] $end
   $var wire 64 + b [63:0] $end
   $var wire 5 - opcode [4:0] $end
   $var wire 64 . result [63:0] $end
   $var wire 1 0 zero $end
   $var wire 1 1 negative $end
   $var wire 1 2 carry_out $end
   $var wire 1 3 overflow $end
   $var wire 64 # sum [63:0] $end
   $var wire 64 % diff [63:0] $end
   $var wire 1 ' carry_add $end
   $var wire 1 ( carry_sub $end
  $upscope $end
 $upscope $end
$enddefinitions $end


#0
b0000000000000000000000000000000000000000000000000000000000011110 #
b0000000000000000000000000000000000000000000000000000000000000000 %
0'
0(
b0000000000000000000000000000000000000000000000000000000000001010 )
b0000000000000000000000000000000000000000000000000000000000010100 +
b00000 -
b0000000000000000000000000000000000000000000000000000000000011110 .
00
01
02
03
#10
b0000000000000000000000000000000000000000000000000000000000000000 #
b0000000000000000000000000000000000000000000000000000000000001010 %
b0000000000000000000000000000000000000000000000000000000000010100 )
b0000000000000000000000000000000000000000000000000000000000001010 +
b00001 -
b0000000000000000000000000000000000000000000000000000000000001010 .
#20
b0000000000000000000000000000000000000000000000000000000000000000 %
b0000000000000000000000000000000000000000000000000000000000000000 )
b0000000000000000000000000000000000000000000000000000000000000000 +
b00000 -
b0000000000000000000000000000000000000000000000000000000000000000 .
10
#30
1'
b1111111111111111111111111111111111111111111111111111111111111111 )
b0000000000000000000000000000000000000000000000000000000000000001 +
12
#40
0'
b1111111111111111000000000000000011111111111111110000000000000000 )
b0000000000000000111111111111111100000000000000001111111111111111 +
b00010 -
02
#50
b0001001000110100010101100111100010011010101111001101111011110000 )
b0000111100001111000011110000111100001111000011110000111100001111 +
b00011 -
b0001111100111111010111110111111110011111101111111101111111111111 .
00
#60
b1111111111111111111111111111111111111111111111111111111111111111 )
b0101010101010101010101010101010101010101010101010101010101010101 +
b00100 -
b1010101010101010101010101010101010101010101010101010101010101010 .
11
#70
b0000000000000000000000000000000000000000000000000000000000000001 )
b0000000000000000000000000000000000000000000000000000000000000001 +
b00101 -
b0000000000000000000000000000000000000000000000000000000000000010 .
01
#80
b0000000000000000000000000000000000000000000000000000000000111111 +
b1000000000000000000000000000000000000000000000000000000000000000 .
11
#90
b1000000000000000000000000000000000000000000000000000000000000000 )
b00110 -
b0000000000000000000000000000000000000000000000000000000000000001 .
01
#100
b0000000000000000000000000000000000000000000000000000000000000001 +
b0100000000000000000000000000000000000000000000000000000000000000 .
#110
b1111111111111111111111111111111111111111111111111111111111111000 )
b0000000000000000000000000000000000000000000000000000000000000010 +
b00111 -
b1111111111111111111111111111111111111111111111111111111111111110 .
11
#120
b1111111111111111111111111111111111111111111111111111111111111111 )
b0000000000000000000000000000000000000000000000000000000000000001 +
b1111111111111111111111111111111111111111111111111111111111111111 .
#130
b1111111111111111111111111111111111111111111111111111111100000000 )
b0000000000000000000000000000000000000000000000000000000000001000 +
#140
b1111111111111111111111111111111111111111111111111111111111111011 )
b0000000000000000000000000000000000000000000000000000000000001010 +
b01000 -
b0000000000000000000000000000000000000000000000000000000000000001 .
01
#150
b0000000000000000000000000000000000000000000000000000000000001010 )
b1111111111111111111111111111111111111111111111111111111111111011 +
b0000000000000000000000000000000000000000000000000000000000000000 .
10
#160
b0000000000000000000000000000000000000000000000000000000001100100 )
b0000000000000000000000000000000000000000000000000000000001100100 +
#170
b0000000000000000000000000000000000000000000000000000000000000101 )
b0000000000000000000000000000000000000000000000000000000000001010 +
b01001 -
b0000000000000000000000000000000000000000000000000000000000000001 .
00
#180
b1111111111111111111111111111111111111111111111111111111111111111 )
b0000000000000000000000000000000000000000000000000000000000000000 +
b0000000000000000000000000000000000000000000000000000000000000000 .
10
#190
b0000000000000000000000000000000000000000000000000000000001100100 )
b0000000000000000000000000000000000000000000000000000000001100100 +
#200
b1000000000000000000000000000000000000000000000000000000000000000 #
b0111111111111111111111111111111111111111111111111111111111111111 )
b0000000000000000000000000000000000000000000000000000000000000001 +
b00000 -
b1000000000000000000000000000000000000000000000000000000000000000 .
00
11
13
#210
b0000000000000000000000000000000000000000000000000000000000000000 #
b0111111111111111111111111111111111111111111111111111111111111111 %
b1000000000000000000000000000000000000000000000000000000000000000 )
b00001 -
b0111111111111111111111111111111111111111111111111111111111111111 .
01
#220
b0000000000000000000000000000000000000000000000000000000000000000 %
b1100101011111110101110101011111011001010111111101011101010111110 )
b1101111010101101101111101110111111011110101011011011111011101111 +
b00100 -
b0001010001010011000001000101000100010100010100110000010001010001 .
03
#230
b0000000000000000000000000000000011111111111111111111111111111111 )
b0000000000000000000000000000000000000000000000000000000000100000 +
b00101 -
b1111111111111111111111111111111100000000000000000000000000000000 .
11
#240
b1111111111111111111111111111111100000000000000000000000000000000 )
b00110 -
b0000000000000000000000000000000011111111111111111111111111111111 .
01
